core.py
appearance_score-0.1.0.dist-info/DESCRIPTION.rst
appearance_score-0.1.0.dist-info/METADATA
appearance_score-0.1.0.dist-info/RECORD
appearance_score-0.1.0.dist-info/WHEEL
appearance_score-0.1.0.dist-info/entry_points.txt
appearance_score-0.1.0.dist-info/metadata.json
appearance_score-0.1.0.dist-info/top_level.txt
