Metadata-Version: 2.0
Name: appearance-score
Version: 0.1.0
Summary: 微软小冰颜值测试命令行工具
Home-page: https://github.com/chenjiandongx/Microsoft-appearance-score
Author: chenjiandongx
Author-email: chenjiandongx@qq.com
License: MIT
Platform: UNKNOWN
Requires-Dist: requests
